sneaky/__init__.py
sneaky/core.py
sneaky/utils.py
sneaky/__metadata__/LICENSE
sneaky/__metadata__/README.md
sneaky/__metadata__/__init__.py
sneaky/__metadata__/requirements.txt
sneaky/chrome/__init__.py
sneaky/chrome/driver.py
sneaky/chrome/utils.py
sneaky/chrome/devtools/__init__.py
sneaky/chrome/devtools/protocol/__init__.py
sneaky/chrome/devtools/protocol/browser.py
sneaky/chrome/devtools/protocol/debugger.py
sneaky/chrome/devtools/protocol/dom.py
sneaky/chrome/devtools/protocol/domdebugger.py
sneaky/chrome/devtools/protocol/emulation.py
sneaky/chrome/devtools/protocol/input.py
sneaky/chrome/devtools/protocol/io.py
sneaky/chrome/devtools/protocol/log.py
sneaky/chrome/devtools/protocol/network.py
sneaky/chrome/devtools/protocol/page.py
sneaky/chrome/devtools/protocol/performance.py
sneaky/chrome/devtools/protocol/profiler.py
sneaky/chrome/devtools/protocol/runtime.py
sneaky/chrome/devtools/protocol/security.py
sneaky/chrome/devtools/protocol/target.py
sneaky-0.5.0.dist-info/METADATA
sneaky-0.5.0.dist-info/WHEEL
sneaky-0.5.0.dist-info/top_level.txt
sneaky-0.5.0.dist-info/RECORD
