Metadata-Version: 2.1
Name: sneaky
Version: 0.5.0
Summary: A sneaky web bot based on Selenium driven by ChromeDriver equipped with undetected-chromedriver (as bot detection bypass), Buster (as a reCAPTCHA solver), eavesdropper (as traffic interceptor), vpncmd (as free VPN rotator) let you breach the Internet as you please.
Home-page: https://github.com/foxe6/
Author: f̣ộx̣ệ6
Author-email: foxe6@protonmail.com
License: AGPL-3.0
Project-URL: Sourcecode, https://github.com/foxe6/sneaky
Project-URL: Documentation, https://github.com/foxe6/sneaky/blob/master/test
Project-URL: Example, https://github.com/foxe6/sneaky/blob/master/sneaky/example
Project-URL: Issues, https://github.com/foxe6/sneaky/issues
Project-URL: Funding, https://paypal.me/foxe6
Project-URL: Say Thanks!, https://saythanks.io/to/foxe6
Keywords: chromedriver undetected detection antibot prevent avoid recaptcha captcha buster solver bypass audio selenium web bot scraper crawler proxy automation browsermob
Platform: UNKNOWN
Classifier: Programming Language :: Python :: 3.9
Classifier: Topic :: Utilities
Classifier: Natural Language :: English
Classifier: Intended Audience :: Developers
Classifier: License :: OSI Approved :: GNU Affero General Public License v3
Classifier: Operating System :: MacOS
Classifier: Operating System :: POSIX
Classifier: Operating System :: Microsoft :: Windows :: Windows 10
Classifier: Development Status :: 5 - Production/Stable
Requires-Python: >=3
Requires-Dist: lxml (>=0.0.1)
Requires-Dist: requests (>=0.0.1)
Requires-Dist: vpncmd (>=0.0.1)
Requires-Dist: omnitools (>=0.0.1)
Requires-Dist: selenium (>=0.0.1)
Requires-Dist: undetected-chromedriver (>=0.0.1)
Requires-Dist: scipy (>=0.0.1)
Requires-Dist: numpy (>=0.0.1)
Requires-Dist: eavesdropper (>=0.0.1)
